compressed_lists/__init__.py
compressed_lists/base.py
compressed_lists/biocframe_list.py
compressed_lists/bool_list.py
compressed_lists/float_list.py
compressed_lists/integer_list.py
compressed_lists/numpy_list.py
compressed_lists/partition.py
compressed_lists/split_generic.py
compressed_lists/string_list.py
compressed_lists-0.4.4.dist-info/licenses/LICENSE.txt
compressed_lists-0.4.4.dist-info/METADATA
compressed_lists-0.4.4.dist-info/WHEEL
compressed_lists-0.4.4.dist-info/top_level.txt
compressed_lists-0.4.4.dist-info/RECORD
