Metadata-Version: 2.4
Name: compressed-lists
Version: 0.4.4
Summary: Memory-efficient container for list-like objects
Home-page: https://github.com/biocpy/compressed-lists
Author: Jayaram Kancherla
Author-email: jayaram.kancherla@gmail.com
License: MIT
Project-URL: Documentation, https://github.com/biocpy/compressed-lists
Platform: any
Classifier: Development Status :: 4 - Beta
Classifier: Programming Language :: Python
Requires-Python: >=3.9
License-File: LICENSE.txt
Requires-Dist: importlib-metadata; python_version < "3.8"
Requires-Dist: biocutils>=0.3.3
Requires-Dist: numpy
Requires-Dist: biocframe>=0.7.2
Provides-Extra: testing
Requires-Dist: setuptools; extra == "testing"
Requires-Dist: pytest; extra == "testing"
Requires-Dist: pytest-cov; extra == "testing"
Dynamic: license-file
